{
    "dim": [
        0,
        0,
        0
    ],
    "left": {
        "dim": [
            0,
            0,
            0
        ],
        "name": "fX1",
        "node": "Feature",
        "symbolic": false,
        "type": 2,
        "value": {
            "dim": [
                0,
                0,
                0
            ],
            "input": {
                "dim": [
                    1,
                    -1,
                    0
                ],
                "name": "front_v",
                "node": "Var",
                "symbolic": false,
                "type": 3
            },
            "node": "UnOp",
            "op": "Angle",
            "symbolic": false,
            "type": 4
        }
    },
    "node": "BinOp",
    "op": "Gt",
    "right": {
        "dim": [
            0,
            0,
            0
        ],
        "left": {
            "dim": [
                0,
                0,
                0
            ],
            "name": "pX1",
            "node": "Param",
            "symbolic": true,
            "type": 2,
            "value": {
                "dim": [
                    0,
                    0,
                    0
                ],
                "node": "Num",
                "symbolic": false,
                "type": 2,
                "value": -4.1331939697265625
            }
        },
        "node": "BinOp",
        "op": "Plus",
        "right": {
            "dim": [
                0,
                0,
                0
            ],
            "name": "pX1A",
            "node": "Param",
            "symbolic": true,
            "type": 2,
            "value": {
                "dim": [
                    0,
                    0,
                    0
                ],
                "node": "Num",
                "symbolic": false,
                "type": 2,
                "value": 0.0
            }
        },
        "symbolic": false,
        "type": 4
    },
    "symbolic": false,
    "type": 4
}
